setup.py
Gaussian_inputfile/__init__.py
Gaussian_inputfile/input_nbo.py
Gaussian_inputfile/input_nics.py
Gaussian_inputfile/input_opt.py
Gaussian_inputfile/input_sp.py
Gaussian_inputfile/inputfile_creation.py
Gaussian_inputfile.egg-info/PKG-INFO
Gaussian_inputfile.egg-info/SOURCES.txt
Gaussian_inputfile.egg-info/dependency_links.txt
Gaussian_inputfile.egg-info/not-zip-safe
Gaussian_inputfile.egg-info/top_level.txt