Metadata-Version: 1.0
Name: Gaussian-inputfile
Version: 0.1
Summary: Create Gaussian inputfiles
Home-page: UNKNOWN
Author: Zhili Wen
Author-email: wenzhili523@gmail.com
License: UNKNOWN
Platform: UNKNOWN
